LICENSE.txt
MANIFEST.in
README.md
setup.py
bin/babymaker
bin/debugmaker
bin/ntpdump
pyBabyMaker/__init__.py
pyBabyMaker/babymaker.py
pyBabyMaker/base.py
pyBabyMaker/dag_resolver.py
pyBabyMaker.egg-info/PKG-INFO
pyBabyMaker.egg-info/SOURCES.txt
pyBabyMaker.egg-info/dependency_links.txt
pyBabyMaker.egg-info/requires.txt
pyBabyMaker.egg-info/top_level.txt
pyBabyMaker/boolean/__init__.py
pyBabyMaker/boolean/syntax.py
pyBabyMaker/boolean/utils.py
pyBabyMaker/cpp_templates/babymaker.cpp
pyBabyMaker/engine/__init__.py
pyBabyMaker/engine/core.py
pyBabyMaker/engine/eval.py
pyBabyMaker/engine/functions.py
pyBabyMaker/engine/identifiers.py
pyBabyMaker/engine/syntax.py
pyBabyMaker/io/NestedYAMLLoader.py
pyBabyMaker/io/TupleDump.py
pyBabyMaker/io/__init__.py
test/test_babymaker.py
test/test_base.py
test/test_boolean_utils.py
test/test_dag_resolver.py
test/test_engine_core.py
test/test_engine_eval.py
test/test_engine_functions.py
test/test_engine_identifiers.py
test/test_engine_syntax.py
test/test_io.py