Metadata-Version: 2.1
Name: pyBabyMaker
Version: 0.4.0
Summary: Python babymaker (flat ntuple generation tool) library
Home-page: https://github.com/umd-lhcb/pyBabyMaker
Author: Yipeng Sun
Author-email: syp@umd.edu
License: UNKNOWN
Platform: UNKNOWN
Classifier: Programming Language :: Python :: 3
Classifier: License :: OSI Approved :: BSD License
Classifier: Operating System :: OS Independent
License-File: LICENSE.txt
